avocavo/__init__.py
avocavo/auth.py
avocavo/auth_supabase.py
avocavo/client.py
avocavo/exceptions.py
avocavo/models.py
avocavo-1.1.1.dist-info/METADATA
avocavo-1.1.1.dist-info/WHEEL
avocavo-1.1.1.dist-info/top_level.txt
avocavo-1.1.1.dist-info/RECORD
