Metadata-Version: 2.4
Name: avocavo
Version: 1.1.1
Summary: Avocavo Python SDK - Nutrition analysis made simple with secure USDA data access
Home-page: https://github.com/avocavo/avocavo-python
Download-URL: https://pypi.org/project/avocavo/
Author: Avocavo
Author-email: api-support@avocavo.com
License: MIT
Project-URL: Documentation, https://nutrition.avocavo.app/docs/python
Project-URL: API Dashboard, https://nutrition.avocavo.app
Project-URL: Bug Tracker, https://github.com/avocavo/avocavo-python/issues
Project-URL: Changelog, https://github.com/avocavo/avocavo-python/blob/main/CHANGELOG.md
Project-URL: Support, https://nutrition.avocavo.app/support
Project-URL: Homepage, https://avocavo.app
Keywords: nutrition,api,usda,food,recipe,health,fitness,calories,macros,nutrients,fooddata,fdc,cooking,meal-planning,diet,wellness,avocavo,secure
Platform: any
Classifier: Development Status :: 5 - Production/Stable
Classifier: Intended Audience :: Developers
Classifier: Intended Audience :: Healthcare Industry
Classifier: Intended Audience :: Science/Research
Classifier: Topic :: Software Development :: Libraries :: Python Modules
Classifier: Topic :: Scientific/Engineering :: Information Analysis
Classifier: Topic :: Internet :: WWW/HTTP :: Dynamic Content
Classifier: Topic :: Database :: Front-Ends
Classifier: License :: OSI Approved :: MIT License
Classifier: Programming Language :: Python :: 3
Classifier: Programming Language :: Python :: 3.8
Classifier: Programming Language :: Python :: 3.9
Classifier: Programming Language :: Python :: 3.10
Classifier: Programming Language :: Python :: 3.11
Classifier: Programming Language :: Python :: 3.12
Classifier: Operating System :: OS Independent
Classifier: Natural Language :: English
Requires-Python: >=3.8
Requires-Dist: requests>=2.28.0
Requires-Dist: keyring>=24.0.0
Requires-Dist: supabase>=2.8.0
Provides-Extra: dev
Requires-Dist: pytest>=7.0; extra == "dev"
Requires-Dist: pytest-cov>=4.0; extra == "dev"
Requires-Dist: black>=23.0; extra == "dev"
Requires-Dist: flake8>=6.0; extra == "dev"
Requires-Dist: mypy>=1.0; extra == "dev"
Requires-Dist: twine>=4.0; extra == "dev"
Requires-Dist: wheel>=0.40; extra == "dev"
Provides-Extra: test
Requires-Dist: pytest>=7.0; extra == "test"
Requires-Dist: pytest-mock>=3.10; extra == "test"
Requires-Dist: responses>=0.23.0; extra == "test"
Requires-Dist: pytest-asyncio>=0.21.0; extra == "test"
Provides-Extra: docs
Requires-Dist: sphinx>=6.0; extra == "docs"
Requires-Dist: sphinx-rtd-theme>=1.2; extra == "docs"
Requires-Dist: myst-parser>=1.0; extra == "docs"
Dynamic: author
Dynamic: author-email
Dynamic: classifier
Dynamic: description
Dynamic: description-content-type
Dynamic: download-url
Dynamic: home-page
Dynamic: keywords
Dynamic: license
Dynamic: platform
Dynamic: project-url
Dynamic: provides-extra
Dynamic: requires-dist
Dynamic: requires-python
Dynamic: summary
